README.rst
deez_py/__init__.py
deez_py/__main__.py
deez_py/deez_ast.py
deez_py/lexer.py
deez_py/parser.py
deez_py/token_types.py
deez_py/tokens.py
deez_py-0.1.6.dist-info/METADATA
deez_py-0.1.6.dist-info/WHEEL
deez_py-0.1.6.dist-info/RECORD
