Metadata-Version: 2.1
Name: deez-py
Version: 0.1.6
Summary: A Python implementation of a lexical analyzer that provides comprehensive scanning, and lookahead capabilities. It also implements a parser that comes with awesome functionalities.
Home-page: https://github.com/ThePrimeagen/ts-rust-zig-deez
License: GNU General Public License v3.0
Keywords: python,deez_py,lexer
Author: Mahmoud Harmouch
Author-email: business@wiseai.dev
Requires-Python: >=3.10,<4.0
Classifier: Development Status :: 2 - Pre-Alpha
Classifier: Intended Audience :: Developers
Classifier: License :: Other/Proprietary License
Classifier: Natural Language :: English
Classifier: Programming Language :: Python :: 3
Classifier: Programming Language :: Python :: 3.10
Classifier: Programming Language :: Python :: 3.11
Project-URL: Repository, https://github.com/ThePrimeagen/ts-rust-zig-deez
